[{"Input sequence ID":"P.putida_alkB","Accession":"WP_011920688.1","% identity":"100","Size":"401","E score":"0"},{"Input sequence ID":"P.putida_alkB","Accession":"AHY94988.1","% identity":"99.751","Size":"401","E score":"0"},{"Input sequence ID":"P.putida_alkB","Accession":"WP_025167106.1","% identity":"89.801","Size":"402","E score":"0"},{"Input sequence ID":"P.putida_alkB","Accession":"WP_022963145.1","% identity":"89.776","Size":"401","E score":"0"},{"Input sequence ID":"P.putida_alkB","Accession":"Q9WWW6.1","% identity":"89.552","Size":"402","E score":"0"},{"Input sequence ID":"P.putida_alkB","Accession":"EPA95341.1","% identity":"88","Size":"400","E score":"0"},{"Input sequence ID":"P.putida_alkB","Accession":"WP_042955520.1","% identity":"88","Size":"400","E score":"0"},{"Input sequence ID":"P.putida_alkB","Accession":"WP_089423379.1","% identity":"79.847","Size":"392","E score":"0"},{"Input sequence ID":"P.putida_alkB","Accession":"RCW72391.1","% identity":"77.635","Size":"389","E score":"0"},{"Input sequence ID":"P.putida_alkB","Accession":"ABM17711.1","% identity":"78.261","Size":"391","E score":"0"},{"Input sequence ID":"P.putida_alkB","Accession":"WP_096346985.1","% identity":"77.635","Size":"389","E score":"0"},{"Input sequence ID":"P.putida_alkB","Accession":"WP_061026539.1","% identity":"81.551","Size":"374","E score":"0"},{"Input sequence ID":"P.putida_alkB","Accession":"WP_041656661.1","% identity":"78.261","Size":"391","E score":"0"},{"Input sequence ID":"P.putida_alkB","Accession":"SFL77349.1","% identity":"77.378","Size":"389","E score":"0"},{"Input sequence ID":"P.putida_alkB","Accession":"WP_031209722.1","% identity":"77.749","Size":"391","E score":"0"},{"Input sequence ID":"P.putida_alkB","Accession":"ERF86596.1","% identity":"81.551","Size":"374","E score":"0"},{"Input sequence ID":"P.putida_alkB","Accession":"KXO07569.1","% identity":"77.635","Size":"389","E score":"0"},{"Input sequence ID":"P.putida_alkB","Accession":"WP_014422298.1","% identity":"77.635","Size":"389","E score":"0"},{"Input sequence ID":"P.putida_alkB","Accession":"WP_119023429.1","% identity":"77.121","Size":"389","E score":"0"},{"Input sequence ID":"P.putida_alkB","Accession":"WP_103970578.1","% identity":"77.062","Size":"388","E score":"0"},{"Input sequence ID":"P.putida_alkB","Accession":"ABM17541.1","% identity":"77.121","Size":"389","E score":"0"},{"Input sequence ID":"P.putida_alkB","Accession":"WP_053115583.1","% identity":"77.378","Size":"389","E score":"0"},{"Input sequence ID":"P.putida_alkB","Accession":"WP_041656636.1","% identity":"77.121","Size":"389","E score":"0"},{"Input sequence ID":"P.putida_alkB","Accession":"ERS88355.1","% identity":"77.179","Size":"390","E score":"0"},{"Input sequence ID":"P.putida_alkB","Accession":"WP_036149232.1","% identity":"77.179","Size":"390","E score":"0"},{"Input sequence ID":"P.putida_alkB","Accession":"PHS50061.1","% identity":"77.692","Size":"390","E score":"0"},{"Input sequence ID":"P.putida_alkB","Accession":"WP_011589978.1","% identity":"77.403","Size":"385","E score":"0"},{"Input sequence ID":"P.putida_alkB","Accession":"ERS06798.1","% identity":"76.215","Size":"391","E score":"0"},{"Input sequence ID":"P.putida_alkB","Accession":"WP_031211538.1","% identity":"76.215","Size":"391","E score":"0"},{"Input sequence ID":"P.putida_alkB","Accession":"WP_035459793.1","% identity":"77.403","Size":"385","E score":"0"},{"Input sequence ID":"P.putida_alkB","Accession":"BAC98365.1","% identity":"77.143","Size":"385","E score":"0"},{"Input sequence ID":"P.putida_alkB","Accession":"WP_031209723.1","% identity":"76.35","Size":"389","E score":"0"},{"Input sequence ID":"P.putida_alkB","Accession":"ERS87385.1","% identity":"76.546","Size":"388","E score":"0"},{"Input sequence ID":"P.putida_alkB","Accession":"PHS50062.1","% identity":"76.546","Size":"388","E score":"0"},{"Input sequence ID":"P.putida_alkB","Accession":"WP_036219382.1","% identity":"75.703","Size":"391","E score":"0"},{"Input sequence ID":"P.putida_alkB","Accession":"WP_067604797.1","% identity":"75.969","Size":"387","E score":"0"},{"Input sequence ID":"P.putida_alkB","Accession":"WP_088626203.1","% identity":"78.877","Size":"374","E score":"0"},{"Input sequence ID":"P.putida_alkB","Accession":"ERP93241.1","% identity":"75.711","Size":"387","E score":"0"},{"Input sequence ID":"P.putida_alkB","Accession":"WP_027238808.1","% identity":"78.877","Size":"374","E score":"0"},{"Input sequence ID":"P.putida_alkB","Accession":"WP_090271078.1","% identity":"78.877","Size":"374","E score":"0"},{"Input sequence ID":"P.putida_alkB","Accession":"WP_111551159.1","% identity":"77.513","Size":"378","E score":"0"},{"Input sequence ID":"P.putida_alkB","Accession":"WP_084394765.1","% identity":"77.807","Size":"374","E score":"0"},{"Input sequence ID":"P.putida_alkB","Accession":"WP_009802138.1","% identity":"77.807","Size":"374","E score":"0"},{"Input sequence ID":"P.putida_alkB","Accession":"OUS22366.1","% identity":"75.844","Size":"385","E score":"0"},{"Input sequence ID":"P.putida_alkB","Accession":"WP_110795640.1","% identity":"75.584","Size":"385","E score":"0"},{"Input sequence ID":"P.putida_alkB","Accession":"WP_009506508.1","% identity":"77.249","Size":"378","E score":"0"},{"Input sequence ID":"P.putida_alkB","Accession":"WP_090257409.1","% identity":"100","Size":"297","E score":"0"},{"Input sequence ID":"P.putida_alkB","Accession":"SSC64660.1","% identity":"71.675","Size":"406","E score":"0"},{"Input sequence ID":"P.putida_alkB","Accession":"WP_115671937.1","% identity":"74.286","Size":"385","E score":"0"},{"Input sequence ID":"P.putida_alkB","Accession":"OYY16981.1","% identity":"73.214","Size":"392","E score":"0"},{"Input sequence ID":"P.putida_alkB","Accession":"CAC86944.1","% identity":"100","Size":"290","E score":"0"},{"Input sequence ID":"P.putida_alkB","Accession":"WP_012275111.1","% identity":"74.541","Size":"381","E score":"0"},{"Input sequence ID":"P.putida_alkB","Accession":"WP_040110213.1","% identity":"71.867","Size":"391","E score":"0"},{"Input sequence ID":"P.putida_alkB","Accession":"AJA11741.1","% identity":"71.867","Size":"391","E score":"0"},{"Input sequence ID":"P.putida_alkB","Accession":"WP_067105300.1","% identity":"71.867","Size":"391","E score":"0"},{"Input sequence ID":"P.putida_alkB","Accession":"WP_119748553.1","% identity":"73.629","Size":"383","E score":"0"},{"Input sequence ID":"P.putida_alkB","Accession":"WP_066044402.1","% identity":"72.063","Size":"383","E score":"0"},{"Input sequence ID":"P.putida_alkB","Accession":"WP_033964747.1","% identity":"73.368","Size":"383","E score":"0"},{"Input sequence ID":"P.putida_alkB","Accession":"ART40166.1","% identity":"72.656","Size":"384","E score":"0"},{"Input sequence ID":"P.putida_alkB","Accession":"WP_043290478.1","% identity":"73.087","Size":"379","E score":"0"},{"Input sequence ID":"P.putida_alkB","Accession":"WP_015486581.1","% identity":"72.751","Size":"378","E score":"0"},{"Input sequence ID":"P.putida_alkB","Accession":"WP_100092258.1","% identity":"71.129","Size":"381","E score":"0"},{"Input sequence ID":"P.putida_alkB","Accession":"ERS87382.1","% identity":"79.179","Size":"341","E score":"0"},{"Input sequence ID":"P.putida_alkB","Accession":"BAP15615.1","% identity":"79.341","Size":"334","E score":"0"},{"Input sequence ID":"P.putida_alkB","Accession":"ART35428.1","% identity":"74.148","Size":"352","E score":"0"},{"Input sequence ID":"P.putida_alkB","Accession":"WP_084339829.1","% identity":"100","Size":"266","E score":"0"},{"Input sequence ID":"P.putida_alkB","Accession":"CAB59525.1","% identity":"94.828","Size":"290","E score":"0"},{"Input sequence ID":"P.putida_alkB","Accession":"ACH99213.1","% identity":"94.483","Size":"290","E score":"0"},{"Input sequence ID":"P.putida_alkB","Accession":"ACH99215.1","% identity":"94.138","Size":"290","E score":"0"},{"Input sequence ID":"P.putida_alkB","Accession":"ACH99216.1","% identity":"93.793","Size":"290","E score":"0"},{"Input sequence ID":"P.putida_alkB","Accession":"WP_100786310.1","% identity":"67.292","Size":"373","E score":"0"},{"Input sequence ID":"P.putida_alkB","Accession":"WP_118981285.1","% identity":"66.667","Size":"375","E score":"0"},{"Input sequence ID":"P.putida_alkB","Accession":"WP_083244131.1","% identity":"67.109","Size":"377","E score":"0"},{"Input sequence ID":"P.putida_alkB","Accession":"WP_118970219.1","% identity":"66.4","Size":"375","E score":"0"},{"Input sequence ID":"P.putida_alkB","Accession":"AOP34841.1","% identity":"67.109","Size":"377","E score":"0"},{"Input sequence ID":"P.putida_alkB","Accession":"AAK56792.1","% identity":"93.793","Size":"290","E score":"0"},{"Input sequence ID":"P.putida_alkB","Accession":"ACH99229.1","% identity":"91.034","Size":"290","E score":"0"},{"Input sequence ID":"P.putida_alkB","Accession":"WP_091535756.1","% identity":"64.439","Size":"374","E score":"2.26E-177"},{"Input sequence ID":"P.putida_alkB","Accession":"SFF66422.1","% identity":"64.439","Size":"374","E score":"2.26E-177"},{"Input sequence ID":"P.putida_alkB","Accession":"AMY71574.1","% identity":"79.725","Size":"291","E score":"7.86E-174"},{"Input sequence ID":"P.putida_alkB","Accession":"ACS91348.1","% identity":"83.146","Size":"267","E score":"1.96E-165"},{"Input sequence ID":"P.putida_alkB","Accession":"AAP41820.1","% identity":"98.678","Size":"227","E score":"5.57E-161"},{"Input sequence ID":"P.putida_alkB","Accession":"WP_009023992.1","% identity":"58.777","Size":"376","E score":"1.35E-156"},{"Input sequence ID":"P.putida_alkB","Accession":"WP_043769838.1","% identity":"58.355","Size":"377","E score":"8.28E-156"},{"Input sequence ID":"P.putida_alkB","Accession":"PLX55814.1","% identity":"55.584","Size":"385","E score":"6.12E-150"},{"Input sequence ID":"P.putida_alkB","Accession":"AER56442.1","% identity":"76.692","Size":"266","E score":"9.67E-150"},{"Input sequence ID":"P.putida_alkB","Accession":"OUX34029.1","% identity":"55.527","Size":"389","E score":"5.79E-148"},{"Input sequence ID":"P.putida_alkB","Accession":"WP_068514162.1","% identity":"54.242","Size":"389","E score":"1.28E-146"},{"Input sequence ID":"P.putida_alkB","Accession":"WP_090196048.1","% identity":"54.66","Size":"397","E score":"1.95E-146"},{"Input sequence ID":"P.putida_alkB","Accession":"OUR97594.1","% identity":"55.108","Size":"372","E score":"8.99E-146"},{"Input sequence ID":"P.putida_alkB","Accession":"KNZ32332.1","% identity":"53.543","Size":"381","E score":"1.02E-145"},{"Input sequence ID":"P.putida_alkB","Accession":"WP_008737102.1","% identity":"54.688","Size":"384","E score":"7.26E-145"},{"Input sequence ID":"P.putida_alkB","Accession":"WP_068638184.1","% identity":"55.145","Size":"379","E score":"1.47E-144"},{"Input sequence ID":"P.putida_alkB","Accession":"WP_068450891.1","% identity":"55.08","Size":"374","E score":"2.70E-144"},{"Input sequence ID":"P.putida_alkB","Accession":"WP_057673738.1","% identity":"54.617","Size":"379","E score":"5.00E-144"},{"Input sequence ID":"P.putida_alkB","Accession":"KZZ43963.1","% identity":"56.131","Size":"367","E score":"1.05E-143"},{"Input sequence ID":"P.putida_alkB","Accession":"WP_071871702.1","% identity":"53.608","Size":"388","E score":"6.61E-143"},{"Input sequence ID":"P.putida_alkB","Accession":"WP_074870650.1","% identity":"55.348","Size":"374","E score":"1.42E-142"},{"Input sequence ID":"P.putida_alkB","Accession":"WP_068507153.1","% identity":"55.285","Size":"369","E score":"1.50E-142"},{"Input sequence ID":"P.putida_alkB","Accession":"WP_022976322.1","% identity":"55.065","Size":"385","E score":"1.76E-142"}]